codius/__init__.py
codius/di.py
codius/domain/__init__.py
codius/domain/model/__init__.py
codius/domain/model/config/__init__.py
codius/domain/model/config/anthropic/__init__.py
codius/domain/model/config/anthropic/anthropic_llm_model.py
codius/domain/model/config/approval_mode.py
codius/domain/model/config/config.py
codius/domain/model/config/llm_provider.py
codius/domain/model/config/ollama/__init__.py
codius/domain/model/config/ollama/ollama_llm_model.py
codius/domain/model/config/openai/__init__.py
codius/domain/model/config/openai/openai_llm_model.py
codius/domain/model/intents/__init__.py
codius/domain/model/intents/aggregate/__init__.py
codius/domain/model/intents/aggregate/add_aggregate_intent.py
codius/domain/model/intents/aggregate/add_aggregate_method_intent.py
codius/domain/model/intents/aggregate/add_aggregate_method_parameter_intent.py
codius/domain/model/intents/aggregate/add_aggregate_property_intent.py
codius/domain/model/intents/aggregate/remove_aggregate_intent.py
codius/domain/model/intents/aggregate/remove_aggregate_method_intent.py
codius/domain/model/intents/aggregate/remove_aggregate_method_parameter_intent.py
codius/domain/model/intents/aggregate/remove_aggregate_property_intent.py
codius/domain/model/intents/composite_intent.py
codius/domain/model/intents/database_provider.py
codius/domain/model/intents/intent_base.py
codius/domain/model/intents/intent_type.py
codius/domain/model/intents/location.py
codius/domain/model/intents/method.py
codius/domain/model/intents/method_implementation.py
codius/domain/model/intents/parameter.py
codius/domain/model/intents/persistence_provider.py
codius/domain/model/intents/property.py
codius/domain/model/intents/repository/__init__.py
codius/domain/model/intents/repository/add_repository_intent.py
codius/domain/model/intents/repository/add_repository_method_intent.py
codius/domain/model/intents/repository/remove_repository_intent.py
codius/domain/model/intents/repository/remove_repository_method_intent.py
codius-0.3.0.dist-info/METADATA
codius-0.3.0.dist-info/WHEEL
codius-0.3.0.dist-info/entry_points.txt
codius-0.3.0.dist-info/RECORD
