Metadata-Version: 2.3
Name: codius
Version: 0.3.0
Summary: A coding assistant for domain-driven design projects in ASP.NET Core.
License: GPLv3
Keywords: ddd,codegen,aspnetcore,cli,assistant
Author: David Runemalm
Author-email: david.runemalm@gmail.com
Requires-Python: >=3.9,!=3.13.*
Classifier: Development Status :: 5 - Production/Stable
Classifier: Intended Audience :: Developers
Classifier: Topic :: Software Development :: Code Generators
Classifier: License :: OSI Approved :: GNU General Public License v3 (GPLv3)
Classifier: Programming Language :: Python :: 3
Classifier: Programming Language :: Python :: 3.9
Classifier: Programming Language :: Python :: 3.10
Classifier: Programming Language :: Python :: 3.11
Classifier: Programming Language :: Python :: 3.12
Requires-Dist: exceptiongroup
Requires-Dist: jinja2
Requires-Dist: langchain-openai
Requires-Dist: langgraph
Requires-Dist: prompt-toolkit
Requires-Dist: py-dependency-injection (>=1.0.0rc2,<2.0.0)
Requires-Dist: python-dateutil
Requires-Dist: python-dotenv
Requires-Dist: pyyaml
Requires-Dist: rich
Requires-Dist: tree-sitter (==0.23.2)
Requires-Dist: tree-sitter-c-sharp
Requires-Dist: typing-extensions
